chanjo/__init__.py
chanjo/calculate.py
chanjo/exc.py
chanjo/sambamba.py
chanjo/sex.py
chanjo/testutils.py
chanjo/cli/__init__.py
chanjo/cli/base.py
chanjo/cli/calculate.py
chanjo/cli/db.py
chanjo/cli/init.py
chanjo/cli/load.py
chanjo/cli/sambamba.py
chanjo/cli/sex.py
chanjo/init/__init__.py
chanjo/init/bootstrap.py
chanjo/init/demo.py
chanjo/init/demo-files/hgnc.min.bed
chanjo/init/demo-files/sample1.coverage.bed
chanjo/init/demo-files/sample2.coverage.bed
chanjo/init/demo-files/sample3.coverage.bed
chanjo/load/__init__.py
chanjo/load/link.py
chanjo/load/sambamba.py
chanjo/load/utils.py
chanjo/load/parse/__init__.py
chanjo/load/parse/bed.py
chanjo/load/parse/sambamba.py
chanjo/store/__init__.py
chanjo/store/api.py
chanjo/store/constants.py
chanjo/store/delete.py
chanjo/store/fetch.py
chanjo/store/models.py
chanjo-4.8.0.dist-info/licenses/AUTHORS
chanjo-4.8.0.dist-info/licenses/LICENSE
chanjo-4.8.0.dist-info/METADATA
chanjo-4.8.0.dist-info/WHEEL
chanjo-4.8.0.dist-info/entry_points.txt
chanjo-4.8.0.dist-info/top_level.txt
chanjo-4.8.0.dist-info/RECORD
