Metadata-Version: 2.4
Name: chanjo
Version: 4.8.0
Summary: Coverage analysis tool for clinical sequencing
Home-page: https://clinical-genomics.github.io/chanjo/
Author: Robin Andeer
Author-email: robin.andeer@gmail.com
License: MIT
Keywords: coverage sequencing clinical exome completeness diagnostics
Classifier: Development Status :: 5 - Production/Stable
Classifier: Intended Audience :: Science/Research
Classifier: Topic :: Software Development
Classifier: Topic :: Scientific/Engineering :: Bio-Informatics
Classifier: License :: OSI Approved :: MIT License
Classifier: Programming Language :: Python :: 3
Classifier: Environment :: Console
License-File: LICENSE
License-File: AUTHORS
Requires-Dist: coloredlogs
Requires-Dist: click
Requires-Dist: cryptography
Requires-Dist: toolz
Requires-Dist: pyyaml
Requires-Dist: importlib_metadata
Requires-Dist: importlib_resources
Requires-Dist: pymysql
Requires-Dist: sqlalchemy>=2.0
Requires-Dist: sqlservice>=3.0
Dynamic: author
Dynamic: author-email
Dynamic: classifier
Dynamic: home-page
Dynamic: keywords
Dynamic: license
Dynamic: license-file
Dynamic: requires-dist
Dynamic: summary
